LearnCTheHardWay/README.md
LearnCTheHardWay/__init__.py
LearnCTheHardWay/__main__.py
LearnCTheHardWay/file.epub
LearnCTheHardWay/index.html
LearnCTheHardWay/css/__init__.py
LearnCTheHardWay/css/annotations.css
LearnCTheHardWay/css/main.css
LearnCTheHardWay/css/normalize.css
LearnCTheHardWay/css/popup.css
LearnCTheHardWay/font/__init__.py
LearnCTheHardWay/font/fontello.eot
LearnCTheHardWay/font/fontello.svg
LearnCTheHardWay/font/fontello.ttf
LearnCTheHardWay/font/fontello.woff
LearnCTheHardWay/img/__init__.py
LearnCTheHardWay/img/annotator-glyph-sprite.png
LearnCTheHardWay/img/annotator-icon-sprite.png
LearnCTheHardWay/img/apple-touch-icon.png
LearnCTheHardWay/img/cancelfullscreen.png
LearnCTheHardWay/img/close.png
LearnCTheHardWay/img/fullscreen.png
LearnCTheHardWay/img/loader.gif
LearnCTheHardWay/img/menu-icon.png
LearnCTheHardWay/img/save.png
LearnCTheHardWay/img/saved.png
LearnCTheHardWay/img/settings-s.png
LearnCTheHardWay/img/settings.png
LearnCTheHardWay/img/star.png
LearnCTheHardWay/js/__init__.py
LearnCTheHardWay/js/epub.js
LearnCTheHardWay/js/epub.min.js
LearnCTheHardWay/js/epub.min.map
LearnCTheHardWay/js/hooks.min.js
LearnCTheHardWay/js/hooks.min.map
LearnCTheHardWay/js/reader.js
LearnCTheHardWay/js/reader.js.map
LearnCTheHardWay/js/reader.min.js
LearnCTheHardWay/js/reader.min.map
LearnCTheHardWay/js/hooks/__init__.py
LearnCTheHardWay/js/hooks/extensions/__init__.py
LearnCTheHardWay/js/hooks/extensions/highlight.js
LearnCTheHardWay/js/libs/__init__.py
LearnCTheHardWay/js/libs/jquery.min.js
LearnCTheHardWay/js/libs/localforage.min.js
LearnCTheHardWay/js/libs/screenfull.js
LearnCTheHardWay/js/libs/screenfull.min.js
LearnCTheHardWay/js/libs/zip.min.js
LearnCTheHardWay/js/plugins/__init__.py
LearnCTheHardWay/js/plugins/hypothesis.js
LearnCTheHardWay/js/plugins/search.js
learn_c_the_hard_way-2024.3.1.0.dist-info/METADATA
learn_c_the_hard_way-2024.3.1.0.dist-info/WHEEL
learn_c_the_hard_way-2024.3.1.0.dist-info/entry_points.txt
learn_c_the_hard_way-2024.3.1.0.dist-info/top_level.txt
learn_c_the_hard_way-2024.3.1.0.dist-info/RECORD
